torchmore/__init__.py
torchmore/combos.py
torchmore/flex.py
torchmore/helpers.py
torchmore/layers.py
torchmore/localimport.py
torchmore-0.1.0.dist-info/LICENSE
torchmore-0.1.0.dist-info/METADATA
torchmore-0.1.0.dist-info/WHEEL
torchmore-0.1.0.dist-info/top_level.txt
torchmore-0.1.0.dist-info/RECORD
