Metadata-Version: 2.1
Name: torchmore
Version: 0.1.0
Summary: Useful additional layers for PyTorch.
Home-page: http://github.com/tmbdev/torchmore
Author: Thomas Breuel
Author-email: tmbdev+removeme@gmail.com
License: MIT
Keywords: object store,client,deep learning
Platform: UNKNOWN
Classifier: Development Status :: 3 - Alpha
Classifier: License :: OSI Approved :: BSD License
Classifier: Programming Language :: Python :: 3.6
Classifier: Programming Language :: Python :: 3.7
Requires-Python: >=3.6
Requires-Dist: Pillow
Requires-Dist: braceexpand
Requires-Dist: msgpack
Requires-Dist: numpy
Requires-Dist: pyyaml
Requires-Dist: scipy
Requires-Dist: simplejson
Requires-Dist: torch
Requires-Dist: torchvision
